__init__.py
__main__.py
notify.py
result.py
sherlock.py
sites.py
resources/data.json
resources/data.schema.json
tests/__init__.py
tests/all.py
tests/base.py
tests/test_multiple_usernames.py
sherlock_project-0.14.4.dist-info/LICENSE
sherlock_project-0.14.4.dist-info/METADATA
sherlock_project-0.14.4.dist-info/WHEEL
sherlock_project-0.14.4.dist-info/entry_points.txt
sherlock_project-0.14.4.dist-info/top_level.txt
sherlock_project-0.14.4.dist-info/RECORD
