Metadata-Version: 2.1
Name: sherlock-project
Version: 0.14.4
Summary: Hunt down social media accounts by username across social networks
Home-page: http://sherlock-project.github.io/
Author: Sherlock Project
Author-email: Siddharth Dushantha <siddharth.dushantha@gmail.com>
Maintainer-email: Paul Pfeister <pypi-contact@pfeister.dev>
License: MIT
Project-URL: Homepage, http://sherlock-project.github.io/
Project-URL: Repository, https://github.com/sherlock-project/sherlock.git
Project-URL: Issues, https://github.com/sherlock-project/sherlock/issues
Keywords: osint,reconnaissance,information gathering
Classifier: Development Status :: 5 - Production/Stable
Classifier: Intended Audience :: Developers
Classifier: Intended Audience :: Information Technology
Classifier: License :: OSI Approved :: MIT License
Classifier: Natural Language :: English
Classifier: Operating System :: OS Independent
Classifier: Programming Language :: Python :: 3
Classifier: Topic :: Security
License-File: LICENSE
Requires-Dist: certifi >=2019.6.16
Requires-Dist: colorama >=0.4.1
Requires-Dist: PySocks >=1.7.0
Requires-Dist: requests >=2.22.0
Requires-Dist: requests-futures >=1.0.0
Requires-Dist: stem >=1.8.0
Requires-Dist: torrequest >=0.1.0
Requires-Dist: pandas >=1.0.0
Requires-Dist: openpyxl >=3.0.10
Requires-Dist: exrex >=0.11.0
